spinqit_simplified/__init__.py
spinqit_simplified/cloud_mcp_submit.py
spinqit_simplified/test.py
spinqit_simplified/backend/__init__.py
spinqit_simplified/backend/backend.py
spinqit_simplified/backend/backend_util.py
spinqit_simplified/backend/qasm_backend.py
spinqit_simplified/backend/spinq_cloud_backend.py
spinqit_simplified/backend/client/__init__.py
spinqit_simplified/backend/client/spinq_cloud_client.py
spinqit_simplified/backend/client/spinq_session.py
spinqit_simplified/backend/layout/__init__.py
spinqit_simplified/backend/layout/layout.py
spinqit_simplified/backend/layout/layout_util.py
spinqit_simplified/backend/layout/physical_layout.py
spinqit_simplified/backend/layout/routing_layout.py
spinqit_simplified/backend/layout/sven_swap_mapper.py
spinqit_simplified/compiler/__init__.py
spinqit_simplified/compiler/compiler.py
spinqit_simplified/compiler/ir.py
spinqit_simplified/compiler/qasm_compiler.py
spinqit_simplified/compiler/qasm/Qasm2ErrorListener.py
spinqit_simplified/compiler/qasm/Qasm2EventListener.py
spinqit_simplified/compiler/qasm/Qasm2Lexer.py
spinqit_simplified/compiler/qasm/Qasm2Listener.py
spinqit_simplified/compiler/qasm/Qasm2Parser.py
spinqit_simplified/compiler/qasm/__init__.py
spinqit_simplified/compiler/translator/__init__.py
spinqit_simplified/compiler/translator/gate_converter.py
spinqit_simplified/compiler/translator/qiskit_to_spinq.py
spinqit_simplified/model/Ising_gate.py
spinqit_simplified/model/__init__.py
spinqit_simplified/model/basic_gate.py
spinqit_simplified/model/circuit.py
spinqit_simplified/model/controlled_gate.py
spinqit_simplified/model/controlled_gate_decomposer.py
spinqit_simplified/model/exceptions.py
spinqit_simplified/model/gates.py
spinqit_simplified/model/instruction.py
spinqit_simplified/model/inverse_builder.py
spinqit_simplified/model/matrix_gate.py
spinqit_simplified/model/multi_control_phase_gate.py
spinqit_simplified/model/parameter.py
spinqit_simplified/model/register.py
spinqit_simplified/model/repeat.py
spinqit_task_env-0.1.0.dist-info/METADATA
spinqit_task_env-0.1.0.dist-info/WHEEL
spinqit_task_env-0.1.0.dist-info/top_level.txt
spinqit_task_env-0.1.0.dist-info/RECORD
